MANIFEST.in
setup.py
FuestcDoor01.egg-info/PKG-INFO
FuestcDoor01.egg-info/SOURCES.txt
FuestcDoor01.egg-info/dependency_links.txt
FuestcDoor01.egg-info/requires.txt
FuestcDoor01.egg-info/top_level.txt
Fuestcdoor/main.py
Fuestcdoor/static/QRcode.html
Fuestcdoor/static/css/app.32e770dd.css
Fuestcdoor/static/css/chunk-2a5e4bc4.ca4f56d8.css
Fuestcdoor/static/css/chunk-vendors.97b05c2c.css
Fuestcdoor/static/css/ionicons.min.css
Fuestcdoor/static/img/46c5701c922b41d5b1cde1d57b77ff21.png
Fuestcdoor/static/img/account.png
Fuestcdoor/static/img/account_multiple.png
Fuestcdoor/static/img/bwc_wechat.d6141ed0.png
Fuestcdoor/static/img/clock.png
Fuestcdoor/static/js/app.599aafe4.js
Fuestcdoor/static/js/chunk-2a5e4bc4.fce45a6b.js
Fuestcdoor/static/js/chunk-2d216d56.3e60dc28.js
Fuestcdoor/static/js/chunk-vendors.98c206fb.js
Fuestcdoor/static/jss/app.599aafe4.js
Fuestcdoor/static/jss/chunk-2a5e4bc4.fce45a6b.js
Fuestcdoor/static/jss/chunk-vendors.98c206fb.js
Fuestcdoor/templates/index.html
Fuestcdoor/templates/index2.html