Metadata-Version: 1.0
Name: FuestcDoor01
Version: 0.0.5
Summary: FuestcDoor
Home-page: UNKNOWN
Author: FuestcDoor01
Author-email: mrlution@qq.com
License: UNKNOWN
Platform: UNKNOWN
